lcm/Q_and_F.py
lcm/__init__.py
lcm/_config.py
lcm/_version.py
lcm/argmax.py
lcm/dispatchers.py
lcm/entry_point.py
lcm/exceptions.py
lcm/function_representation.py
lcm/functools.py
lcm/grid_helpers.py
lcm/grids.py
lcm/interfaces.py
lcm/logging.py
lcm/mark.py
lcm/max_Q_over_c.py
lcm/max_Qc_over_d.py
lcm/ndimage.py
lcm/next_state.py
lcm/py.typed
lcm/random.py
lcm/state_action_space.py
lcm/typing.py
lcm/user_model.py
lcm/utils.py
lcm/input_processing/__init__.py
lcm/input_processing/create_params_template.py
lcm/input_processing/process_model.py
lcm/input_processing/util.py
lcm/simulation/__init__.py
lcm/simulation/processing.py
lcm/simulation/simulate.py
lcm/solution/__init__.py
lcm/solution/solve_brute.py
pylcm-0.0.1.dist-info/METADATA
pylcm-0.0.1.dist-info/WHEEL
pylcm-0.0.1.dist-info/licenses/LICENSE
pylcm-0.0.1.dist-info/RECORD
