Metadata-Version: 2.4
Name: pylcm
Version: 0.0.1
Summary: Specification, solution, and simulation of finite-horizon dynamic choice models.
Project-URL: Repository, https://github.com/opensourceeconomics/pylcm
Project-URL: Github, https://github.com/opensourceeconomics/pylcm
Project-URL: Tracker, https://github.com/opensourceeconomics/pylcm/issues
Author: Janos Gabler
Author-email: Tim Mensinger <mensingertim@gmail.com>
Maintainer-email: Tim Mensinger <mensingertim@gmail.com>, Hans-Martin von Gaudecker <hmgaudecker@uni-bonn.de>
License: Copyright (c) 2023 The PyLCM Authors
License-File: LICENSE
Keywords: Dynamic programming,Econometrics,Economics,Estimation,Life cycle models,Statistics
Classifier: Development Status :: 3 - Alpha
Classifier: Intended Audience :: Science/Research
Classifier: License :: OSI Approved :: Apache Software License
Classifier: Operating System :: MacOS :: MacOS X
Classifier: Operating System :: Microsoft :: Windows
Classifier: Operating System :: POSIX
Classifier: Operating System :: Unix
Classifier: Programming Language :: Python :: 3.12
Classifier: Topic :: Scientific/Engineering
Classifier: Typing :: Typed
Requires-Python: >=3.12
Requires-Dist: dags>=0.3.0
Requires-Dist: jax>=0.5.1
Requires-Dist: pandas
